mdkair.py
mdk/compiler.py
mdk/compiler.pyi
mdk/resources/__init__.py
mdk/resources/__init__.pyi
mdk/resources/animation.py
mdk/resources/animation.pyi
mdk/stdlib/__init__.py
mdk/stdlib/__init__.pyi
mdk/stdlib/controllers.py
mdk/stdlib/controllers.pyi
mdk/stdlib/mtl.py
mdk/stdlib/mtl.pyi
mdk/stdlib/redirects.py
mdk/stdlib/redirects.pyi
mdk/stdlib/triggers.py
mdk/stdlib/triggers.pyi
mdk/types/__init__.py
mdk/types/__init__.pyi
mdk/types/builtins.py
mdk/types/builtins.pyi
mdk/types/context.py
mdk/types/context.pyi
mdk/types/defined.py
mdk/types/defined.pyi
mdk/types/enums.py
mdk/types/enums.pyi
mdk/types/errors.py
mdk/types/errors.pyi
mdk/types/expressions.py
mdk/types/expressions.pyi
mdk/types/specifier.py
mdk/types/specifier.pyi
mdk/types/variables.py
mdk/types/variables.pyi
mdk/utils/__init__.py
mdk/utils/__init__.pyi
mdk/utils/animation.py
mdk/utils/compiler.py
mdk/utils/compiler.pyi
mdk/utils/controllers.py
mdk/utils/controllers.pyi
mdk/utils/expressions.py
mdk/utils/expressions.pyi
mdk/utils/sff.py
mdk/utils/shared.py
mdk/utils/shared.pyi
mdk/utils/triggers.py
mdk/utils/triggers.pyi
mdk_mugen-0.2.2.dist-info/METADATA
mdk_mugen-0.2.2.dist-info/WHEEL
mdk_mugen-0.2.2.dist-info/entry_points.txt
mdk_mugen-0.2.2.dist-info/RECORD
