Metadata-Version: 2.4
Name: mdk-mugen
Version: 0.2.2
Project-URL: Repository, https://github.com/ZiddiaMUGEN/MDK
Project-URL: Documentation, https://github.com/ZiddiaMUGEN/MDK/blob/main/mdk-python/TUTORIAL.md
Project-URL: Changelog, https://github.com/ZiddiaMUGEN/MDK/releases
Requires-Dist: mtl-mugen>=0.2.2
Requires-Dist: pyqt6>=6.10.1
